BMCToolkit.pyd
BMCToolkit-stubs/__init__.pyi
BMCToolkit-0.10.0.dist-info/METADATA
BMCToolkit-0.10.0.dist-info/WHEEL
BMCToolkit-0.10.0.dist-info/top_level.txt
BMCToolkit-0.10.0.dist-info/RECORD
