Metadata-Version: 2.1
Name: BMCToolkit
Version: 0.10.0
Summary: Simulate and analyze trajectories of Block Markov Chains.
Author: Jaron Sanders
Author-email: jaron.sanders@tue.nl
Project-URL: Source, https://gitlab.tue.nl/acss/public/detection-and-evaluation-of-clusters-within-sequential-data
Classifier: Development Status :: 3 - Alpha
Classifier: Environment :: GPU :: NVIDIA CUDA
Classifier: License :: OSI Approved :: Mozilla Public License 2.0 (MPL 2.0)
Classifier: Operating System :: Microsoft :: Windows
Classifier: Programming Language :: C++
Classifier: Programming Language :: Python :: 3.9
Classifier: Programming Language :: Python :: 3.10
Classifier: Programming Language :: Python :: 3.11
Classifier: Topic :: Scientific/Engineering :: Mathematics
Requires-Python: >=3.9.6
Requires-Dist: numpy>=1.23.1
